sshdb/__init__.py
sshdb/__main__.py
sshdb/constants.py
sshdb/logger.py
sshdb/manager.py
sshdb-0.0.2.dist-info/LICENSE.md
sshdb-0.0.2.dist-info/METADATA
sshdb-0.0.2.dist-info/WHEEL
sshdb-0.0.2.dist-info/entry_points.txt
sshdb-0.0.2.dist-info/top_level.txt
sshdb-0.0.2.dist-info/RECORD
